crc_jupyter_auth/__init__.py
crc_jupyter_auth/remote_user_auth.py
crc_jupyter_auth-1.1.0.dist-info/LICENSE.md
crc_jupyter_auth-1.1.0.dist-info/METADATA
crc_jupyter_auth-1.1.0.dist-info/WHEEL
crc_jupyter_auth-1.1.0.dist-info/RECORD
