Metadata-Version: 2.1
Name: crc_jupyter_auth
Version: 1.1.0
Summary: Jupyter authentication plugin that checks for account existence and VPN roles.
Home-page: https://github.com/pitt-crc/Jupyter-Authenticator
License: GPL-3.0-only
Keywords: Pitt,CRC,Jupyter,JupyterHub,JupyterLab,Authentication
Author: Pitt Center for Research Computing
Requires-Python: >=3.7
Classifier: Framework :: Jupyter
Classifier: Framework :: Jupyter :: JupyterLab
Classifier: Intended Audience :: System Administrators
Classifier: License :: OSI Approved :: GNU General Public License v3 (GPLv3)
Classifier: Natural Language :: English
Classifier: Operating System :: OS Independent
Classifier: Programming Language :: Python
Classifier: Programming Language :: Python :: 3
Classifier: Programming Language :: Python :: 3.7
Classifier: Programming Language :: Python :: 3.8
Classifier: Programming Language :: Python :: 3.9
Classifier: Programming Language :: Python :: 3.10
Classifier: Programming Language :: Python :: 3.11
Classifier: Topic :: System :: Systems Administration
Requires-Dist: jupyterhub
Requires-Dist: tornado
Requires-Dist: traitlets
Project-URL: Documentation, https://github.com/pitt-crc/Jupyter-Authenticator
Project-URL: Repository, https://github.com/pitt-crc/Jupyter-Authenticator
